django_spaghetti/.github/workflows/ci.yml
django_spaghetti/__init__.py
django_spaghetti/locale/en/LC_MESSAGES/django.po
django_spaghetti/locale/fr/LC_MESSAGES/django.po
django_spaghetti/templates/django_spaghetti/meatball.html
django_spaghetti/templates/django_spaghetti/plate.html
django_spaghetti/tests/__init__.py
django_spaghetti/tests/models.py
django_spaghetti/tests/settings.py
django_spaghetti/tests/templates/tests/home_plate.html
django_spaghetti/tests/templates/tests/meatball.html
django_spaghetti/tests/test_it.py
django_spaghetti/tests/urls.py
django_spaghetti/urls.py
django_spaghetti/views.py
django_spaghetti_and_meatballs-0.4.2.dist-info/LICENSE
django_spaghetti_and_meatballs-0.4.2.dist-info/WHEEL
django_spaghetti_and_meatballs-0.4.2.dist-info/METADATA
django_spaghetti_and_meatballs-0.4.2.dist-info/RECORD
