Metadata-Version: 2.1
Name: django-spaghetti-and-meatballs
Version: 0.4.2
Summary: Its a spicy meatball for serving up fresh hot entity-relationship diagrams straight from your django models.
License: MIT
Author: Samuel Spencer
Author-email: sam@sqbl.org
Requires-Python: >=3.6,<4.0
Classifier: License :: OSI Approved :: MIT License
Classifier: Programming Language :: Python :: 3
Classifier: Programming Language :: Python :: 3.6
Classifier: Programming Language :: Python :: 3.7
Classifier: Programming Language :: Python :: 3.8
Classifier: Programming Language :: Python :: 3.9
Requires-Dist: django (>=2.2)
